odoo10_addon_medical_pathology_import-10.0.1.0.0-py2.7-nspkg.pth
odoo/addons/medical_pathology_import/README.rst
odoo/addons/medical_pathology_import/__init__.py
odoo/addons/medical_pathology_import/__manifest__.py
odoo/addons/medical_pathology_import/static/description/icon.png
odoo/addons/medical_pathology_import/tests/__init__.py
odoo/addons/medical_pathology_import/tests/test_medical_pathology_import.py
odoo/addons/medical_pathology_import/wizards/__init__.py
odoo/addons/medical_pathology_import/wizards/medical_pathology_import.py
odoo/addons/medical_pathology_import/wizards/medical_pathology_import.xml
odoo10_addon_medical_pathology_import-10.0.1.0.0.dist-info/DESCRIPTION.rst
odoo10_addon_medical_pathology_import-10.0.1.0.0.dist-info/METADATA
odoo10_addon_medical_pathology_import-10.0.1.0.0.dist-info/RECORD
odoo10_addon_medical_pathology_import-10.0.1.0.0.dist-info/WHEEL
odoo10_addon_medical_pathology_import-10.0.1.0.0.dist-info/metadata.json
odoo10_addon_medical_pathology_import-10.0.1.0.0.dist-info/namespace_packages.txt
odoo10_addon_medical_pathology_import-10.0.1.0.0.dist-info/top_level.txt
